setup.py
moyo/HTTPerror.py
moyo/__init__.py
moyo/plugins.py
moyo/server.py
moyo/session.py
moyo.egg-info/PKG-INFO
moyo.egg-info/SOURCES.txt
moyo.egg-info/dependency_links.txt
moyo.egg-info/requires.txt
moyo.egg-info/top_level.txt